MANIFEST.in
README.rst
RELEASE-VERSION
readme.md
requirements.txt
setup.cfg
setup.py
version.py
quite/__init__.py
quite/deferred_function.py
quite.egg-info/PKG-INFO
quite.egg-info/SOURCES.txt
quite.egg-info/dependency_links.txt
quite.egg-info/requires.txt
quite.egg-info/top_level.txt
quite/controller/__init__.py
quite/controller/dialog_ui_controller.py
quite/controller/file_dialog_controller.py
quite/controller/widget_controller.py
quite/controller/widget_ui_controller.py
quite/core/__init__.py
quite/core/event_loop.py
quite/core/qt_core.py
quite/core/timer.py
quite/gui/__init__.py
quite/gui/qt_gui.py
quite/gui/ui_extension.py
quite/gui/interfaces/__init__.py
quite/gui/interfaces/base_interface.py
quite/gui/interfaces/changed_signal_interface.py
quite/gui/interfaces/closed_signal_interface.py
quite/gui/interfaces/excited_signal_interface.py
quite/gui/interfaces/focus_in_signal_interface.py
quite/gui/interfaces/focus_out_signal_interface.py
quite/gui/interfaces/row_changed_signal_interface.py
quite/gui/interfaces/showed_signal_interface.py
quite/gui/interfaces/ability_interfaces/__init__.py
quite/gui/interfaces/ability_interfaces/class_exec_interface.py
quite/gui/interfaces/ability_interfaces/container_ability_interface.py
quite/gui/layouts/__init__.py
quite/gui/layouts/square_layout.py
quite/gui/paint/__init__.py
quite/gui/paint/painter.py
quite/gui/paint/pen.py
quite/gui/paint/point.py
quite/gui/paint/scaling.py
quite/gui/paint/size.py
quite/gui/widgets/__init__.py
quite/gui/widgets/action.py
quite/gui/widgets/combo_box.py
quite/gui/widgets/date_edit.py
quite/gui/widgets/date_time_edit.py
quite/gui/widgets/dialog.py
quite/gui/widgets/dock_widget.py
quite/gui/widgets/double_spin_box.py
quite/gui/widgets/group_box.py
quite/gui/widgets/input_dialog.py
quite/gui/widgets/label.py
quite/gui/widgets/layout.py
quite/gui/widgets/line_edit.py
quite/gui/widgets/list_widget.py
quite/gui/widgets/main_window.py
quite/gui/widgets/plot_widget.py
quite/gui/widgets/push_button.py
quite/gui/widgets/radio_button.py
quite/gui/widgets/shortcut.py
quite/gui/widgets/spin_box.py
quite/gui/widgets/table_view.py
