Metadata-Version: 1.1
Name: quite
Version: 0.4.8
Summary: QT UI Extension
Home-page: https://github.com/KD-Group/quite
Author: SF-Zhou
Author-email: sfzhou.scut@gmail.com
License: MIT
Keywords: qt ui
Platform: UNKNOWN
Classifier: Development Status :: 3 - Alpha
Classifier: Intended Audience :: Developers
Classifier: License :: OSI Approved :: MIT License
Classifier: Programming Language :: Python :: 3
Classifier: Programming Language :: Python :: 3.3
Classifier: Programming Language :: Python :: 3.4
